ldt/__init__.py
ldt/core.py
ldt/errors.py
ldt/fields.py
ldt/io_drives/__init__.py
ldt/io_drives/protocols.py
ldt/io_drives/store.py
ldt/io_drives/drivers/__init__.py
ldt/io_drives/drivers/base.py
ldt/io_drives/drivers/extra.py
ldt/io_drives/drivers/standard.py
ldt_nexus-1.0.2.dist-info/METADATA
ldt_nexus-1.0.2.dist-info/WHEEL
ldt_nexus-1.0.2.dist-info/RECORD
