Metadata-Version: 2.4
Name: ldt-nexus
Version: 1.0.2
Summary: Reactive data-tree management with pathlib-hybrid interface
Author: SnayperTihCreator
Requires-Python: >=3.11
Requires-Dist: attrs>=23.1.0
Provides-Extra: all
Requires-Dist: json5>=0.9.14; extra == 'all'
Requires-Dist: pyyaml>=6.0; extra == 'all'
Requires-Dist: toml>=0.10.2; extra == 'all'
Provides-Extra: json5
Requires-Dist: json5>=0.9.14; extra == 'json5'
Provides-Extra: toml
Requires-Dist: toml>=0.10.2; extra == 'toml'
Provides-Extra: yaml
Requires-Dist: pyyaml>=6.0; extra == 'yaml'
